{"elements":[{"from":[7.9572086,8.048324,-15.822254],"to":[8.071494,8.162609,-13.685112],"rotation":{"angle":0.0,"axis":"y","origin":[8.0,8.0,8.0]},"faces":{"east":{"uv":[0.0,0.935,0.935,0.985],"rotation":0,"texture":"#1","tintindex":0},"south":{"uv":[1.92,0.935,1.97,0.985],"rotation":0,"texture":"#1","tintindex":0},"north":{"uv":[0.935,0.935,0.985,0.985],"rotation":0,"texture":"#1","tintindex":0},"west":{"uv":[0.985,0.935,1.92,0.985],"rotation":0,"texture":"#1","tintindex":0},"up":{"uv":[0.985,0.935,0.935,0.0],"rotation":0,"texture":"#1","tintindex":0},"down":{"uv":[1.035,0.0,0.985,0.935],"rotation":0,"texture":"#1","tintindex":0}}}],"textures":{"1":"modelengine:entity/bloque_tronco"},"display":{"head":{"translation":[0.0,-6.4,0.0],"scale":[4.0,4.0,4.0]}}}