{"elements":[{"from":[7.542857,31.77143,8.036109],"to":[8.457143,32.0,8.721824],"rotation":{"angle":0.0,"axis":"y","origin":[8.0,31.885715,8.378966]},"faces":{"east":{"uv":[0.0,0.3,0.3,0.4],"rotation":90,"texture":"#1","tintindex":0},"south":{"uv":[1.0,0.3,1.4,0.4],"rotation":0,"texture":"#1","tintindex":0},"north":{"uv":[0.3,0.3,0.7,0.4],"rotation":0,"texture":"#1","tintindex":0},"west":{"uv":[0.7,0.3,1.0,0.4],"rotation":90,"texture":"#1","tintindex":0},"up":{"uv":[0.7,0.3,0.3,0.0],"rotation":0,"texture":"#1","tintindex":0},"down":{"uv":[1.1,0.0,0.7,0.3],"rotation":0,"texture":"#1","tintindex":0}}},{"from":[7.5468464,28.111382,8.046144],"to":[7.775418,31.768524,8.731857],"rotation":{"angle":0.0,"axis":"y","origin":[7.661132,29.939953,8.389]},"faces":{"east":{"uv":[0.0,0.3,0.3,1.9],"rotation":90,"texture":"#1","tintindex":0},"south":{"uv":[0.7,0.3,0.8,1.9],"rotation":90,"texture":"#1","tintindex":0},"north":{"uv":[0.3,0.3,0.4,1.9],"rotation":90,"texture":"#1","tintindex":0},"west":{"uv":[0.4,0.3,0.7,1.9],"rotation":90,"texture":"#1","tintindex":0},"up":{"uv":[0.4,0.3,0.3,0.0],"rotation":90,"texture":"#1","tintindex":0},"down":{"uv":[0.5,0.0,0.4,0.3],"rotation":90,"texture":"#1","tintindex":0}}},{"from":[8.23256,28.111382,8.046144],"to":[8.461132,31.768524,8.731857],"rotation":{"angle":0.0,"axis":"y","origin":[8.346847,29.939953,8.389]},"faces":{"east":{"uv":[0.0,0.3,0.3,1.9],"rotation":90,"texture":"#1","tintindex":0},"south":{"uv":[0.7,0.3,0.8,1.9],"rotation":90,"texture":"#1","tintindex":0},"north":{"uv":[0.3,0.3,0.4,1.9],"rotation":90,"texture":"#1","tintindex":0},"west":{"uv":[0.4,0.3,0.7,1.9],"rotation":90,"texture":"#1","tintindex":0},"up":{"uv":[0.4,0.3,0.3,0.0],"rotation":90,"texture":"#1","tintindex":0},"down":{"uv":[0.5,0.0,0.4,0.3],"rotation":90,"texture":"#1","tintindex":0}}}],"textures":{"1":"modelengine:entity/bloque_tronco"},"display":{"head":{"translation":[0.0,-2.603705,0.0],"scale":[4.0,4.0,4.0]}}}