{"elements":[{"from":[7.7714286,27.984116,16.255842],"to":[8.457143,30.726976,16.941555],"rotation":{"angle":0.0,"axis":"y","origin":[8.0,8.0,8.0]},"faces":{"east":{"uv":[0.0,0.3,0.3,1.5],"rotation":0,"texture":"#1","tintindex":0},"south":{"uv":[0.9,0.3,1.2,1.5],"rotation":0,"texture":"#1","tintindex":0},"north":{"uv":[0.3,0.3,0.6,1.5],"rotation":0,"texture":"#1","tintindex":0},"west":{"uv":[0.6,0.3,0.9,1.5],"rotation":0,"texture":"#1","tintindex":0},"up":{"uv":[0.6,0.3,0.3,0.0],"rotation":0,"texture":"#1","tintindex":0},"down":{"uv":[0.9,0.0,0.6,0.3],"rotation":0,"texture":"#1","tintindex":0}}}],"textures":{"1":"modelengine:entity/bloque_tronco"},"display":{"head":{"translation":[0.0,-6.4,0.0],"scale":[4.0,4.0,4.0]}}}